{
  "BasicLayers": [
    {
      "Agents": [
        {
          "ConstructorParameterMapping": [
            {
              "AllowedValues": {
                "type": "string"
              },
              "ColumnName": null,
              "Name": "identifier",
              "TableName": null
            },
            {
              "AllowedValues": {
                "type": "string"
              },
              "ColumnName": null,
              "Name": "format",
              "TableName": null
            },
            {
              "AllowedValues": {
                "type": "string"
              },
              "ColumnName": null,
              "Name": "source",
              "TableName": null
            }
          ],
          "FullName": "ImmuneSystemModel.AntigenInformationLayer.AntigenInformationProviderAgent",
          "InstanceCount": null,
          "MetaDataId": null,
          "Name": "AntigenInformationProviderAgent"
        }
      ],
      "LayerName": "AntigenInformationLayer"
    },
    {
      "Agents": [
        {
          "ConstructorParameterMapping": [
            {
              "AllowedValues": {
                "type": "string"
              },
              "ColumnName": null,
              "Name": "areaName",
              "TableName": null
            },
            {
              "AllowedValues": {
                "maximum": 2147483647,
                "minimum": -2147483648,
                "type": "integer"
              },
              "ColumnName": null,
              "Name": "activateAfter",
              "TableName": null
            },
            {
              "AllowedValues": {
                "maximum": 2147483647,
                "minimum": -2147483648,
                "type": "integer"
              },
              "ColumnName": null,
              "Name": "numOfCopies",
              "TableName": null
            },
            {
              "AllowedValues": {
                "type": "number"
              },
              "ColumnName": null,
              "Name": "x",
              "TableName": null
            },
            {
              "AllowedValues": {
                "type": "number"
              },
              "ColumnName": null,
              "Name": "y",
              "TableName": null
            },
            {
              "AllowedValues": {
                "type": "number"
              },
              "ColumnName": null,
              "Name": "z",
              "TableName": null
            },
            {
              "AllowedValues": {
                "maximum": 2147483647,
                "minimum": -2147483648,
                "type": "integer"
              },
              "ColumnName": null,
              "Name": "lifeZone1",
              "TableName": null
            },
            {
              "AllowedValues": {
                "maximum": 2147483647,
                "minimum": -2147483648,
                "type": "integer"
              },
              "ColumnName": null,
              "Name": "lifeZone2",
              "TableName": null
            },
            {
              "AllowedValues": {
                "maximum": 2147483647,
                "minimum": -2147483648,
                "type": "integer"
              },
              "ColumnName": null,
              "Name": "lifeZone3",
              "TableName": null
            },
            {
              "AllowedValues": {
                "maximum": 2147483647,
                "minimum": -2147483648,
                "type": "integer"
              },
              "ColumnName": null,
              "Name": "durationAbZone1",
              "TableName": null
            },
            {
              "AllowedValues": {
                "maximum": 2147483647,
                "minimum": -2147483648,
                "type": "integer"
              },
              "ColumnName": null,
              "Name": "durationAb1Zone2",
              "TableName": null
            },
            {
              "AllowedValues": {
                "maximum": 2147483647,
                "minimum": -2147483648,
                "type": "integer"
              },
              "ColumnName": null,
              "Name": "durationAb2Zone2",
              "TableName": null
            },
            {
              "AllowedValues": {
                "maximum": 2147483647,
                "minimum": -2147483648,
                "type": "integer"
              },
              "ColumnName": null,
              "Name": "durationAbZone3",
              "TableName": null
            },
            {
              "AllowedValues": {
                "maximum": 2147483647,
                "minimum": -2147483648,
                "type": "integer"
              },
              "ColumnName": null,
              "Name": "numberOfClones",
              "TableName": null
            },
            {
              "AllowedValues": {
                "type": "string"
              },
              "ColumnName": null,
              "Name": "bcellReceptorIdentifier",
              "TableName": null
            },
            {
              "AllowedValues": {
                "type": "string"
              },
              "ColumnName": null,
              "Name": "parameterSetName",
              "TableName": null
            }
          ],
          "FullName": "ImmuneSystemModel.ImmuneSystemLayer.BCell",
          "InstanceCount": null,
          "MetaDataId": null,
          "Name": "BCell"
        },
        {
          "ConstructorParameterMapping": [
            {
              "AllowedValues": {
                "type": "string"
              },
              "ColumnName": null,
              "Name": "areaName",
              "TableName": null
            },
            {
              "AllowedValues": {
                "maximum": 2147483647,
                "minimum": -2147483648,
                "type": "integer"
              },
              "ColumnName": null,
              "Name": "activateAfter",
              "TableName": null
            },
            {
              "AllowedValues": {
                "maximum": 2147483647,
                "minimum": -2147483648,
                "type": "integer"
              },
              "ColumnName": null,
              "Name": "numOfCopies",
              "TableName": null
            },
            {
              "AllowedValues": {
                "type": "number"
              },
              "ColumnName": null,
              "Name": "x",
              "TableName": null
            },
            {
              "AllowedValues": {
                "type": "number"
              },
              "ColumnName": null,
              "Name": "y",
              "TableName": null
            },
            {
              "AllowedValues": {
                "type": "number"
              },
              "ColumnName": null,
              "Name": "z",
              "TableName": null
            },
            {
              "AllowedValues": {
                "maximum": 2147483647,
                "minimum": -2147483648,
                "type": "integer"
              },
              "ColumnName": null,
              "Name": "durationCK1Zone1",
              "TableName": null
            },
            {
              "AllowedValues": {
                "maximum": 2147483647,
                "minimum": -2147483648,
                "type": "integer"
              },
              "ColumnName": null,
              "Name": "durationCK1Zone2",
              "TableName": null
            },
            {
              "AllowedValues": {
                "maximum": 2147483647,
                "minimum": -2147483648,
                "type": "integer"
              },
              "ColumnName": null,
              "Name": "lifeZone1",
              "TableName": null
            },
            {
              "AllowedValues": {
                "maximum": 2147483647,
                "minimum": -2147483648,
                "type": "integer"
              },
              "ColumnName": null,
              "Name": "lifeZone2",
              "TableName": null
            },
            {
              "AllowedValues": {
                "maximum": 2147483647,
                "minimum": -2147483648,
                "type": "integer"
              },
              "ColumnName": null,
              "Name": "numberOfCTLToProduce",
              "TableName": null
            },
            {
              "AllowedValues": {
                "maximum": 2147483647,
                "minimum": -2147483648,
                "type": "integer"
              },
              "ColumnName": null,
              "Name": "numberOfTicksNoCK1orPK1",
              "TableName": null
            },
            {
              "AllowedValues": {
                "type": "string"
              },
              "ColumnName": null,
              "Name": "parameterSetName",
              "TableName": null
            },
            {
              "AllowedValues": {
                "type": "string"
              },
              "ColumnName": null,
              "Name": "tCellReceptorName",
              "TableName": null
            }
          ],
          "FullName": "ImmuneSystemModel.ImmuneSystemLayer.CytotoxicTCell",
          "InstanceCount": null,
          "MetaDataId": null,
          "Name": "CytotoxicTCell"
        },
        {
          "ConstructorParameterMapping": [
            {
              "AllowedValues": {
                "type": "string"
              },
              "ColumnName": null,
              "Name": "areaName",
              "TableName": null
            },
            {
              "AllowedValues": {
                "maximum": 2147483647,
                "minimum": -2147483648,
                "type": "integer"
              },
              "ColumnName": null,
              "Name": "activateAfter",
              "TableName": null
            },
            {
              "AllowedValues": {
                "maximum": 2147483647,
                "minimum": -2147483648,
                "type": "integer"
              },
              "ColumnName": null,
              "Name": "numOfCopies",
              "TableName": null
            },
            {
              "AllowedValues": {
                "type": "number"
              },
              "ColumnName": null,
              "Name": "x",
              "TableName": null
            },
            {
              "AllowedValues": {
                "type": "number"
              },
              "ColumnName": null,
              "Name": "y",
              "TableName": null
            },
            {
              "AllowedValues": {
                "type": "number"
              },
              "ColumnName": null,
              "Name": "z",
              "TableName": null
            },
            {
              "AllowedValues": {
                "maximum": 2147483647,
                "minimum": -2147483648,
                "type": "integer"
              },
              "ColumnName": null,
              "Name": "durationMK1Zone1",
              "TableName": null
            },
            {
              "AllowedValues": {
                "maximum": 2147483647,
                "minimum": -2147483648,
                "type": "integer"
              },
              "ColumnName": null,
              "Name": "durationMK2Zone1",
              "TableName": null
            },
            {
              "AllowedValues": {
                "maximum": 2147483647,
                "minimum": -2147483648,
                "type": "integer"
              },
              "ColumnName": null,
              "Name": "lifeZone1",
              "TableName": null
            },
            {
              "AllowedValues": {
                "maximum": 2147483647,
                "minimum": -2147483648,
                "type": "integer"
              },
              "ColumnName": null,
              "Name": "lifeZone2",
              "TableName": null
            },
            {
              "AllowedValues": {
                "maximum": 2147483647,
                "minimum": -2147483648,
                "type": "integer"
              },
              "ColumnName": null,
              "Name": "numberOfDendriticCellsToSend",
              "TableName": null
            },
            {
              "AllowedValues": {
                "maximum": 2147483647,
                "minimum": -2147483648,
                "type": "integer"
              },
              "ColumnName": null,
              "Name": "numberOfMakrophagesToSend",
              "TableName": null
            },
            {
              "AllowedValues": {
                "maximum": 2147483647,
                "minimum": -2147483648,
                "type": "integer"
              },
              "ColumnName": null,
              "Name": "numberOfNaturalKillerCellsToSend",
              "TableName": null
            },
            {
              "AllowedValues": {
                "type": "boolean"
              },
              "ColumnName": null,
              "Name": "inflammatory",
              "TableName": null
            },
            {
              "AllowedValues": {
                "maximum": 2147483647,
                "minimum": -2147483648,
                "type": "integer"
              },
              "ColumnName": null,
              "Name": "apoptosisThreshold",
              "TableName": null
            },
            {
              "AllowedValues": {
                "maximum": 2147483647,
                "minimum": -2147483648,
                "type": "integer"
              },
              "ColumnName": null,
              "Name": "durationMKZone2",
              "TableName": null
            },
            {
              "AllowedValues": {
                "type": "string"
              },
              "ColumnName": null,
              "Name": "parameterSetName",
              "TableName": null
            },
            {
              "AllowedValues": {
                "maximum": 2147483647,
                "minimum": -2147483648,
                "type": "integer"
              },
              "ColumnName": null,
              "Name": "maxNumberOfTCellContacts",
              "TableName": null
            }
          ],
          "FullName": "ImmuneSystemModel.ImmuneSystemLayer.DendriticCell",
          "InstanceCount": null,
          "MetaDataId": null,
          "Name": "DendriticCell"
        },
        {
          "ConstructorParameterMapping": [
            {
              "AllowedValues": {
                "type": "string"
              },
              "ColumnName": null,
              "Name": "areaName",
              "TableName": null
            },
            {
              "AllowedValues": {
                "maximum": 2147483647,
                "minimum": -2147483648,
                "type": "integer"
              },
              "ColumnName": null,
              "Name": "activateAfter",
              "TableName": null
            },
            {
              "AllowedValues": {
                "maximum": 2147483647,
                "minimum": -2147483648,
                "type": "integer"
              },
              "ColumnName": null,
              "Name": "numOfCopies",
              "TableName": null
            },
            {
              "AllowedValues": {
                "type": "number"
              },
              "ColumnName": null,
              "Name": "x",
              "TableName": null
            },
            {
              "AllowedValues": {
                "type": "number"
              },
              "ColumnName": null,
              "Name": "y",
              "TableName": null
            },
            {
              "AllowedValues": {
                "type": "number"
              },
              "ColumnName": null,
              "Name": "z",
              "TableName": null
            },
            {
              "AllowedValues": {
                "maximum": 2147483647,
                "minimum": -2147483648,
                "type": "integer"
              },
              "ColumnName": null,
              "Name": "lifeZone1",
              "TableName": null
            },
            {
              "AllowedValues": {
                "type": "string"
              },
              "ColumnName": null,
              "Name": "parameterSetName",
              "TableName": null
            }
          ],
          "FullName": "ImmuneSystemModel.ImmuneSystemLayer.Granulocyte",
          "InstanceCount": null,
          "MetaDataId": null,
          "Name": "Granulocyte"
        },
        {
          "ConstructorParameterMapping": [
            {
              "AllowedValues": {
                "type": "string"
              },
              "ColumnName": null,
              "Name": "areaName",
              "TableName": null
            },
            {
              "AllowedValues": {
                "maximum": 2147483647,
                "minimum": -2147483648,
                "type": "integer"
              },
              "ColumnName": null,
              "Name": "activateAfter",
              "TableName": null
            },
            {
              "AllowedValues": {
                "maximum": 2147483647,
                "minimum": -2147483648,
                "type": "integer"
              },
              "ColumnName": null,
              "Name": "numOfCopies",
              "TableName": null
            },
            {
              "AllowedValues": {
                "type": "number"
              },
              "ColumnName": null,
              "Name": "x",
              "TableName": null
            },
            {
              "AllowedValues": {
                "type": "number"
              },
              "ColumnName": null,
              "Name": "y",
              "TableName": null
            },
            {
              "AllowedValues": {
                "type": "number"
              },
              "ColumnName": null,
              "Name": "z",
              "TableName": null
            },
            {
              "AllowedValues": {
                "maximum": 2147483647,
                "minimum": -2147483648,
                "type": "integer"
              },
              "ColumnName": null,
              "Name": "lifeZone1",
              "TableName": null
            },
            {
              "AllowedValues": {
                "maximum": 2147483647,
                "minimum": -2147483648,
                "type": "integer"
              },
              "ColumnName": null,
              "Name": "durationMK1ProductionZone1",
              "TableName": null
            },
            {
              "AllowedValues": {
                "maximum": 2147483647,
                "minimum": -2147483648,
                "type": "integer"
              },
              "ColumnName": null,
              "Name": "durationMK2ProductionZone1",
              "TableName": null
            },
            {
              "AllowedValues": {
                "maximum": 2147483647,
                "minimum": -2147483648,
                "type": "integer"
              },
              "ColumnName": null,
              "Name": "makrophage1To2ApoptosisThreshold",
              "TableName": null
            },
            {
              "AllowedValues": {
                "type": "string"
              },
              "ColumnName": null,
              "Name": "parameterSetName",
              "TableName": null
            }
          ],
          "FullName": "ImmuneSystemModel.ImmuneSystemLayer.Makrophage",
          "InstanceCount": null,
          "MetaDataId": null,
          "Name": "Makrophage"
        },
        {
          "ConstructorParameterMapping": [
            {
              "AllowedValues": {
                "type": "string"
              },
              "ColumnName": null,
              "Name": "areaName",
              "TableName": null
            },
            {
              "AllowedValues": {
                "maximum": 2147483647,
                "minimum": -2147483648,
                "type": "integer"
              },
              "ColumnName": null,
              "Name": "activateAfter",
              "TableName": null
            },
            {
              "AllowedValues": {
                "maximum": 2147483647,
                "minimum": -2147483648,
                "type": "integer"
              },
              "ColumnName": null,
              "Name": "numOfCopies",
              "TableName": null
            },
            {
              "AllowedValues": {
                "type": "number"
              },
              "ColumnName": null,
              "Name": "x",
              "TableName": null
            },
            {
              "AllowedValues": {
                "type": "number"
              },
              "ColumnName": null,
              "Name": "y",
              "TableName": null
            },
            {
              "AllowedValues": {
                "type": "number"
              },
              "ColumnName": null,
              "Name": "z",
              "TableName": null
            },
            {
              "AllowedValues": {
                "maximum": 2147483647,
                "minimum": -2147483648,
                "type": "integer"
              },
              "ColumnName": null,
              "Name": "lifeZone1",
              "TableName": null
            },
            {
              "AllowedValues": {
                "maximum": 2147483647,
                "minimum": -2147483648,
                "type": "integer"
              },
              "ColumnName": null,
              "Name": "durationCK1ProductionZone1",
              "TableName": null
            },
            {
              "AllowedValues": {
                "maximum": 2147483647,
                "minimum": -2147483648,
                "type": "integer"
              },
              "ColumnName": null,
              "Name": "maxNumOfTicksWithoutKill",
              "TableName": null
            },
            {
              "AllowedValues": {
                "maximum": 2147483647,
                "minimum": -2147483648,
                "type": "integer"
              },
              "ColumnName": null,
              "Name": "killLimit",
              "TableName": null
            },
            {
              "AllowedValues": {
                "type": "string"
              },
              "ColumnName": null,
              "Name": "parameterSetName",
              "TableName": null
            }
          ],
          "FullName": "ImmuneSystemModel.ImmuneSystemLayer.NaturalKillerCell",
          "InstanceCount": null,
          "MetaDataId": null,
          "Name": "NaturalKillerCell"
        },
        {
          "ConstructorParameterMapping": [
            {
              "AllowedValues": {
                "type": "string"
              },
              "ColumnName": null,
              "Name": "areaName",
              "TableName": null
            },
            {
              "AllowedValues": {
                "maximum": 2147483647,
                "minimum": -2147483648,
                "type": "integer"
              },
              "ColumnName": null,
              "Name": "activateAfter",
              "TableName": null
            },
            {
              "AllowedValues": {
                "maximum": 2147483647,
                "minimum": -2147483648,
                "type": "integer"
              },
              "ColumnName": null,
              "Name": "numOfCopies",
              "TableName": null
            },
            {
              "AllowedValues": {
                "type": "number"
              },
              "ColumnName": null,
              "Name": "x",
              "TableName": null
            },
            {
              "AllowedValues": {
                "type": "number"
              },
              "ColumnName": null,
              "Name": "y",
              "TableName": null
            },
            {
              "AllowedValues": {
                "type": "number"
              },
              "ColumnName": null,
              "Name": "z",
              "TableName": null
            },
            {
              "AllowedValues": {
                "type": "string"
              },
              "ColumnName": null,
              "Name": "synchronizedSignalsList",
              "TableName": null
            },
            {
              "AllowedValues": {
                "type": "string"
              },
              "ColumnName": null,
              "Name": "passingAgentsList",
              "TableName": null
            },
            {
              "AllowedValues": {
                "type": "boolean"
              },
              "ColumnName": null,
              "Name": "outputPortal",
              "TableName": null
            },
            {
              "AllowedValues": {
                "type": "number"
              },
              "ColumnName": null,
              "Name": "checkParenchymalCellsRadius",
              "TableName": null
            },
            {
              "AllowedValues": {
                "maximum": 2147483647,
                "minimum": -2147483648,
                "type": "integer"
              },
              "ColumnName": null,
              "Name": "numberOfPCThresholdToFunction",
              "TableName": null
            },
            {
              "AllowedValues": {
                "type": "string"
              },
              "ColumnName": null,
              "Name": "watchedAgentsList",
              "TableName": null
            },
            {
              "AllowedValues": {
                "type": "string"
              },
              "ColumnName": null,
              "Name": "watchedSignalsList",
              "TableName": null
            },
            {
              "AllowedValues": {
                "type": "string"
              },
              "ColumnName": null,
              "Name": "parameterSetName",
              "TableName": null
            }
          ],
          "FullName": "ImmuneSystemModel.ImmuneSystemLayer.Portal",
          "InstanceCount": null,
          "MetaDataId": null,
          "Name": "Portal"
        },
        {
          "ConstructorParameterMapping": [
            {
              "AllowedValues": {
                "type": "string"
              },
              "ColumnName": null,
              "Name": "areaName",
              "TableName": null
            },
            {
              "AllowedValues": {
                "maximum": 2147483647,
                "minimum": -2147483648,
                "type": "integer"
              },
              "ColumnName": null,
              "Name": "activateAfter",
              "TableName": null
            },
            {
              "AllowedValues": {
                "maximum": 2147483647,
                "minimum": -2147483648,
                "type": "integer"
              },
              "ColumnName": null,
              "Name": "numOfCopies",
              "TableName": null
            },
            {
              "AllowedValues": {
                "type": "number"
              },
              "ColumnName": null,
              "Name": "x",
              "TableName": null
            },
            {
              "AllowedValues": {
                "type": "number"
              },
              "ColumnName": null,
              "Name": "y",
              "TableName": null
            },
            {
              "AllowedValues": {
                "type": "number"
              },
              "ColumnName": null,
              "Name": "z",
              "TableName": null
            },
            {
              "AllowedValues": {
                "maximum": 2147483647,
                "minimum": -2147483648,
                "type": "integer"
              },
              "ColumnName": null,
              "Name": "lifeZone1",
              "TableName": null
            },
            {
              "AllowedValues": {
                "maximum": 2147483647,
                "minimum": -2147483648,
                "type": "integer"
              },
              "ColumnName": null,
              "Name": "lifeZone2",
              "TableName": null
            },
            {
              "AllowedValues": {
                "maximum": 2147483647,
                "minimum": -2147483648,
                "type": "integer"
              },
              "ColumnName": null,
              "Name": "lifeMemoryCellZone2",
              "TableName": null
            },
            {
              "AllowedValues": {
                "maximum": 2147483647,
                "minimum": -2147483648,
                "type": "integer"
              },
              "ColumnName": null,
              "Name": "durationCK1Zone2",
              "TableName": null
            },
            {
              "AllowedValues": {
                "maximum": 2147483647,
                "minimum": -2147483648,
                "type": "integer"
              },
              "ColumnName": null,
              "Name": "durationCK2Zone2",
              "TableName": null
            },
            {
              "AllowedValues": {
                "maximum": 2147483647,
                "minimum": -2147483648,
                "type": "integer"
              },
              "ColumnName": null,
              "Name": "CK1Threshold",
              "TableName": null
            },
            {
              "AllowedValues": {
                "maximum": 2147483647,
                "minimum": -2147483648,
                "type": "integer"
              },
              "ColumnName": null,
              "Name": "CK2Threshold",
              "TableName": null
            },
            {
              "AllowedValues": {
                "maximum": 2147483647,
                "minimum": -2147483648,
                "type": "integer"
              },
              "ColumnName": null,
              "Name": "maxNumberOfKills",
              "TableName": null
            },
            {
              "AllowedValues": {
                "maximum": 2147483647,
                "minimum": -2147483648,
                "type": "integer"
              },
              "ColumnName": null,
              "Name": "extraLifeForFirstKill",
              "TableName": null
            },
            {
              "AllowedValues": {
                "type": "string"
              },
              "ColumnName": null,
              "Name": "tCellReceptor",
              "TableName": null
            },
            {
              "AllowedValues": {
                "maximum": 2147483647,
                "minimum": -2147483648,
                "type": "integer"
              },
              "ColumnName": null,
              "Name": "numT1ToSend",
              "TableName": null
            },
            {
              "AllowedValues": {
                "maximum": 2147483647,
                "minimum": -2147483648,
                "type": "integer"
              },
              "ColumnName": null,
              "Name": "numT2ToSend",
              "TableName": null
            },
            {
              "AllowedValues": {
                "type": "string"
              },
              "ColumnName": null,
              "Name": "parameterSetName",
              "TableName": null
            }
          ],
          "FullName": "ImmuneSystemModel.ImmuneSystemLayer.THelperCell",
          "InstanceCount": null,
          "MetaDataId": null,
          "Name": "THelperCell"
        },
        {
          "ConstructorParameterMapping": [
            {
              "AllowedValues": {
                "type": "string"
              },
              "ColumnName": null,
              "Name": "areaName",
              "TableName": null
            },
            {
              "AllowedValues": {
                "maximum": 2147483647,
                "minimum": -2147483648,
                "type": "integer"
              },
              "ColumnName": null,
              "Name": "activateAfter",
              "TableName": null
            },
            {
              "AllowedValues": {
                "maximum": 2147483647,
                "minimum": -2147483648,
                "type": "integer"
              },
              "ColumnName": null,
              "Name": "numOfCopies",
              "TableName": null
            },
            {
              "AllowedValues": {
                "type": "number"
              },
              "ColumnName": null,
              "Name": "x",
              "TableName": null
            },
            {
              "AllowedValues": {
                "type": "number"
              },
              "ColumnName": null,
              "Name": "y",
              "TableName": null
            },
            {
              "AllowedValues": {
                "type": "number"
              },
              "ColumnName": null,
              "Name": "z",
              "TableName": null
            },
            {
              "AllowedValues": {
                "type": "string"
              },
              "ColumnName": null,
              "Name": "antigenIdentifier",
              "TableName": null
            },
            {
              "AllowedValues": {
                "type": "string"
              },
              "ColumnName": null,
              "Name": "targets",
              "TableName": null
            },
            {
              "AllowedValues": {
                "maximum": 2147483647,
                "minimum": -2147483648,
                "type": "integer"
              },
              "ColumnName": null,
              "Name": "life",
              "TableName": null
            },
            {
              "AllowedValues": {
                "maximum": 2147483647,
                "minimum": -2147483648,
                "type": "integer"
              },
              "ColumnName": null,
              "Name": "viralInfectionThreshold",
              "TableName": null
            },
            {
              "AllowedValues": {
                "maximum": 2147483647,
                "minimum": -2147483648,
                "type": "integer"
              },
              "ColumnName": null,
              "Name": "numberToReproduce",
              "TableName": null
            },
            {
              "AllowedValues": {
                "type": "string"
              },
              "ColumnName": null,
              "Name": "parameterSetName",
              "TableName": null
            }
          ],
          "FullName": "ImmuneSystemModel.ImmuneSystemLayer.Virus",
          "InstanceCount": null,
          "MetaDataId": null,
          "Name": "Virus"
        },
        {
          "ConstructorParameterMapping": [
            {
              "AllowedValues": {
                "type": "string"
              },
              "ColumnName": null,
              "Name": "areaName",
              "TableName": null
            },
            {
              "AllowedValues": {
                "maximum": 2147483647,
                "minimum": -2147483648,
                "type": "integer"
              },
              "ColumnName": null,
              "Name": "activateAfter",
              "TableName": null
            },
            {
              "AllowedValues": {
                "maximum": 2147483647,
                "minimum": -2147483648,
                "type": "integer"
              },
              "ColumnName": null,
              "Name": "numOfCopies",
              "TableName": null
            },
            {
              "AllowedValues": {
                "type": "number"
              },
              "ColumnName": null,
              "Name": "x",
              "TableName": null
            },
            {
              "AllowedValues": {
                "type": "number"
              },
              "ColumnName": null,
              "Name": "y",
              "TableName": null
            },
            {
              "AllowedValues": {
                "type": "number"
              },
              "ColumnName": null,
              "Name": "z",
              "TableName": null
            },
            {
              "AllowedValues": {
                "maximum": 2147483647,
                "minimum": -2147483648,
                "type": "integer"
              },
              "ColumnName": null,
              "Name": "stressDuration",
              "TableName": null
            },
            {
              "AllowedValues": {
                "maximum": 2147483647,
                "minimum": -2147483648,
                "type": "integer"
              },
              "ColumnName": null,
              "Name": "ab1LysisThreshold",
              "TableName": null
            },
            {
              "AllowedValues": {
                "maximum": 2147483647,
                "minimum": -2147483648,
                "type": "integer"
              },
              "ColumnName": null,
              "Name": "regenerationTime",
              "TableName": null
            },
            {
              "AllowedValues": {
                "type": "string"
              },
              "ColumnName": null,
              "Name": "parameterSetName",
              "TableName": null
            }
          ],
          "FullName": "ImmuneSystemModel.ImmuneSystemLayer.ParenchymalCell",
          "InstanceCount": null,
          "MetaDataId": null,
          "Name": "ParenchymalCell"
        }
      ],
      "LayerName": "ImmuneSystemLayer"
    },
    {
      "Agents": [
        {
          "ConstructorParameterMapping": [
            {
              "AllowedValues": {
                "type": "string"
              },
              "ColumnName": null,
              "Name": "name",
              "TableName": null
            },
            {
              "AllowedValues": {
                "type": "number"
              },
              "ColumnName": null,
              "Name": "width",
              "TableName": null
            },
            {
              "AllowedValues": {
                "type": "number"
              },
              "ColumnName": null,
              "Name": "height",
              "TableName": null
            },
            {
              "AllowedValues": {
                "type": "number"
              },
              "ColumnName": null,
              "Name": "depth",
              "TableName": null
            },
            {
              "AllowedValues": {
                "type": "boolean"
              },
              "ColumnName": null,
              "Name": "toroidal",
              "TableName": null
            }
          ],
          "FullName": "AreaLayer.AreaPropertiesProviderAgent",
          "InstanceCount": null,
          "MetaDataId": null,
          "Name": "AreaPropertiesProviderAgent"
        }
      ],
      "LayerName": "AreaLayer"
    }
  ],
  "GISLayers": [],
  "TimeSeriesLayers": []
}
